mitoclass/__init__.py
mitoclass/_pretreat.py
mitoclass/_processor.py
mitoclass/_utils.py
mitoclass/_widget.py
mitoclass/napari.yaml
mitoclass/_tests/__init__.py
mitoclass/_tests/test_reader.py
mitoclass/_tests/test_sample_data.py
mitoclass/_tests/test_widget.py
mitoclass/_tests/test_writer.py
mitoclass-1.0.3.dist-info/licenses/LICENSE
mitoclass-1.0.3.dist-info/METADATA
mitoclass-1.0.3.dist-info/WHEEL
mitoclass-1.0.3.dist-info/entry_points.txt
mitoclass-1.0.3.dist-info/top_level.txt
mitoclass-1.0.3.dist-info/RECORD
