Metadata-Version: 2.4
Name: mitoclass
Version: 1.0.3
Summary: MitoClass is a napari plugin for classifying mitochondrial morphology from microscopy images: it allows preprocessing data, predicting classes (connected, fragmented, intermediate), visualizing overlays and 3D summaries, and managing a prediction history.
Author: Jules Malard, David Rousseau, Arnaud Chevrollier
License: 
Project-URL: Documentation, https://github.com/malardjules/MitoClass/blob/master/README.md
Project-URL: Source Code, https://github.com/malardjules/MitoClass
Classifier: Development Status :: 5 - Production/Stable
Classifier: Framework :: napari
Classifier: Intended Audience :: Developers
Classifier: License :: OSI Approved :: GNU General Public License v3 (GPLv3)
Classifier: Operating System :: OS Independent
Classifier: Programming Language :: Python
Classifier: Programming Language :: Python :: 3
Classifier: Programming Language :: Python :: 3 :: Only
Classifier: Programming Language :: Python :: 3.10
Classifier: Programming Language :: Python :: 3.11
Classifier: Programming Language :: Python :: 3.12
Classifier: Programming Language :: Python :: 3.13
Classifier: Topic :: Scientific/Engineering :: Image Processing
Requires-Python: >=3.10
License-File: LICENSE
Requires-Dist: numpy
Requires-Dist: magicgui
Requires-Dist: qtpy
Requires-Dist: scikit-image
Requires-Dist: tifffile
Requires-Dist: tensorflow
Requires-Dist: pandas
Requires-Dist: scikit-learn
Requires-Dist: plotly
Requires-Dist: napari[all]
Provides-Extra: all
Requires-Dist: napari[all]; extra == "all"
Provides-Extra: testing
Requires-Dist: tox; extra == "testing"
Requires-Dist: pytest; extra == "testing"
Requires-Dist: pytest-cov; extra == "testing"
Requires-Dist: pytest-qt; extra == "testing"
Requires-Dist: napari[qt]; extra == "testing"
Dynamic: license-file
